neverlate/__init__.py
neverlate/constants.py
neverlate/credentials.json
neverlate/event_alerter.py
neverlate/google_cal_downloader.py
neverlate/login_dialog.py
neverlate/main.py
neverlate/main_dialog.py
neverlate/pop_up_alert.py
neverlate/preferences.py
neverlate/preferences_dialog.py
neverlate/utils.py
neverlate/images/alarm.png
neverlate/images/clock_big.png
neverlate/images/dismiss.png
neverlate/images/reload.png
neverlate/images/tray_icon.png
neverlate/images/video.png
neverlate/images/warning.png
neverlate/images/zzz.png
neverlate-0.3.0.dist-info/LICENSE
neverlate-0.3.0.dist-info/METADATA
neverlate-0.3.0.dist-info/WHEEL
neverlate-0.3.0.dist-info/entry_points.txt
neverlate-0.3.0.dist-info/top_level.txt
neverlate-0.3.0.dist-info/RECORD
